hypixel_stats/__init__.py
hypixel_stats/api.py
hypixel_stats/exceptions.py
hypixel_stats/games/__init__.py
hypixel_stats/games/bedwars.py
hypixel_stats/games/build_battle.py
hypixel_stats/games/murder_mystery.py
hypixel_stats/games/skywars.py
hypixel_stats/utils/__init__.py
hypixel_stats/utils/formatter.py
hypixelstats_core-0.1.1.dist-info/licenses/LICENSE.txt
hypixelstats_core-0.1.1.dist-info/METADATA
hypixelstats_core-0.1.1.dist-info/WHEEL
hypixelstats_core-0.1.1.dist-info/top_level.txt
hypixelstats_core-0.1.1.dist-info/RECORD
