Metadata-Version: 2.4
Name: hypixelstats-core
Version: 0.1.1
Summary: A lightweight Hypixel statistics module.
Author: seolhwa
License: Custom
Classifier: Programming Language :: Python :: 3
Classifier: Operating System :: OS Independent
Requires-Python: >=3.7
License-File: LICENSE.txt
Dynamic: author
Dynamic: classifier
Dynamic: description
Dynamic: description-content-type
Dynamic: license
Dynamic: license-file
Dynamic: requires-python
Dynamic: summary
